bulwark/__init__.py
bulwark/checks.py
bulwark/decorators.py
bulwark/generic.py
bulwark/project_info.py
bulwark-0.4.2.dist-info/LICENSE
bulwark-0.4.2.dist-info/METADATA
bulwark-0.4.2.dist-info/WHEEL
bulwark-0.4.2.dist-info/top_level.txt
bulwark-0.4.2.dist-info/RECORD
