Metadata-Version: 2.1
Name: bulwark
Version: 0.4.2
Summary: A python package for defensive data analysis.
Home-page: https://github.com/zaxr/bulwark
Author: Zax Rosenberg
Author-email: zaxr@protonmail.com
License: UNKNOWN
Keywords: data analysis testing
Platform: UNKNOWN
Classifier: Development Status :: 3 - Alpha
Classifier: Intended Audience :: Developers
Classifier: License :: OSI Approved :: GNU General Public License v3 (GPLv3)
Classifier: Natural Language :: English
Classifier: Programming Language :: Python :: 3
Classifier: Programming Language :: Python :: 3.5
Classifier: Programming Language :: Python :: 3.6
Classifier: Programming Language :: Python :: 3.7
Requires-Dist: numpy (>=1.8)
Requires-Dist: pandas (>=0.16.2)
Requires-Dist: six (>=1.10.0)
Provides-Extra: dev
Requires-Dist: coverage ; extra == 'dev'
Requires-Dist: pytest ; extra == 'dev'
Requires-Dist: setuptools (>=30.4) ; extra == 'dev'
Requires-Dist: Sphinx ; extra == 'dev'
Requires-Dist: sphinx-rtd-theme ; extra == 'dev'
Provides-Extra: docs
Requires-Dist: setuptools (>=30.4) ; extra == 'docs'
Requires-Dist: Sphinx ; extra == 'docs'
Requires-Dist: sphinx-rtd-theme ; extra == 'docs'
Provides-Extra: test
Requires-Dist: coverage ; extra == 'test'
Requires-Dist: pytest ; extra == 'test'
